dpongpy/__init__.py
dpongpy/__main__.py
dpongpy/controller/__init__.py
dpongpy/controller/local.py
dpongpy/log.py
dpongpy/model.py
dpongpy/remote/__init__.py
dpongpy/remote/centralised/__init__.py
dpongpy/remote/presentation.py
dpongpy/remote/udp.py
dpongpy/view.py
dpongpy-1.1.0.dist-info/LICENSE
dpongpy-1.1.0.dist-info/METADATA
dpongpy-1.1.0.dist-info/WHEEL
dpongpy-1.1.0.dist-info/entry_points.txt
dpongpy-1.1.0.dist-info/RECORD
