Metadata-Version: 2.1
Name: dpongpy
Version: 1.1.0
Summary: Didactical implementation of PONG as an online multiplayer game, aimed at exemplifying distributed systems
License: Apache 2.0
Author: Giovanni Ciatto
Author-email: giovanni.ciatto@unibo.it
Requires-Python: >=3.10.0,<4.0.0
Classifier: License :: Other/Proprietary License
Classifier: Programming Language :: Python :: 3
Classifier: Programming Language :: Python :: 3.10
Classifier: Programming Language :: Python :: 3.11
Classifier: Programming Language :: Python :: 3.12
Requires-Dist: pygame (>=2.6.0,<3.0.0)
